setup.cfg
setup.py
django_migration_control.egg-info/PKG-INFO
django_migration_control.egg-info/SOURCES.txt
django_migration_control.egg-info/dependency_links.txt
django_migration_control.egg-info/top_level.txt
migration_control/__init__.py
migration_control/mixins.py
migration_control/db/__init__.py
migration_control/db/models.py