Metadata-Version: 1.1
Name: django-migration-control
Version: 0.1.2
Summary: Django migration control allows avoid unnecessary migrations such as changing help_text or verbose_name of fields
Home-page: https://github.com/FeroxTL/django-migration-control
Author: Makarov Yurii
Author-email: winnerer@ya.ru
License: MIT
Platform: UNKNOWN
Classifier: Development Status :: 4 - Beta
Classifier: Environment :: Console
Classifier: Intended Audience :: Developers
Classifier: License :: OSI Approved :: MIT License
Classifier: Operating System :: POSIX
Classifier: Operating System :: Unix
Classifier: Programming Language :: Python
